<?xml version="1.0" encoding="UTF-8" standalone="no"?><document setID="ad8916e7-206e-409e-2582-30d072845dd4"><labelDrug name="Atropine Sulfate"><Normalization/></labelDrug><generic name="ATROPINE SULFATE"/><sentence id="Dailymed.ad8916e7-206e-409e-2582-30d072845dd4.s.1" text="Drug Label for drug brand Atropine Sulfate, containing ATROPINE SULFATE." type="negative"><entity charOffset="26:42" id="Dailymed.ad8916e7-206e-409e-2582-30d072845dd4.s.1.e.0" text="atropine sulfate" type="Biomedical_Entity"><Normalization><mmtx cui="C0596005" phraseText="Drug Label for drug brand Atropine Sulfate," preferredWord="Atropine Sulfate" semType="phsu, orch"/><RxNorm RxCui="1223"/></Normalization></entity><entity charOffset="55:71" id="Dailymed.ad8916e7-206e-409e-2582-30d072845dd4.s.1.e.1" text="atropine sulfate" type="Biomedical_Entity"><Normalization><mmtx cui="C0596005" phraseText="ATROPINE SULFATE." preferredWord="Atropine Sulfate" semType="phsu, orch"/><RxNorm RxCui="1223"/></Normalization></entity><entity charOffset="0:19" id="Dailymed.ad8916e7-206e-409e-2582-30d072845dd4.s.1.e.2" text="drug drug" type="Biomedical_Entity"><Normalization><mmtx cui="C0013231" phraseText="Drug Label for drug brand Atropine Sulfate," preferredWord="Drugs, Non-Prescription" semType="phsu"/><RxNorm RxCui="NA"/></Normalization></entity><pair ddi="false" e1="Dailymed.ad8916e7-206e-409e-2582-30d072845dd4.s.1.e.2" e2="Dailymed.ad8916e7-206e-409e-2582-30d072845dd4.s.1.e.0"/><pair ddi="false" e1="Dailymed.ad8916e7-206e-409e-2582-30d072845dd4.s.1.e.2" e2="Dailymed.ad8916e7-206e-409e-2582-30d072845dd4.s.1.e.1"/></sentence><sentence biomedicalEntities="2" id="Dailymed.ad8916e7-206e-409e-2582-30d072845dd4.s.7" lineNumber="13" text="Atropine I.V. decreased the rate of mexiletine absorption without altering the relative oral bioavailability, this delay in mexiletine absorption was reversed by the combination of atropine and intravenous metoclopramide during pretreatment for anesthesia. " type="regular"><entity charOffset="14:35|47:57" id="Dailymed.ad8916e7-206e-409e-2582-30d072845dd4.s.7.e.1" text="decreased the rate of absorption" type="Decrease_Interaction"/><entity charOffset="36:46" id="Dailymed.ad8916e7-206e-409e-2582-30d072845dd4.s.7.e.2" text="mexiletine" type="Drug"><Normalization><mmtx cui="C0025887" phraseText="the rate of mexiletine absorption" preferredWord="Mexiletine" semType="phsu, orch"/><RxNorm RxCui="6926"/></Normalization></entity><entity charOffset="0:13" id="Dailymed.ad8916e7-206e-409e-2582-30d072845dd4.s.7.e.3" text="Atropine I.V." type="Drug"><Normalization><mmtx cui="C0004259" phraseText="Atropine" preferredWord="Atropine" semType="phsu, orch"/><mmtx cui="C1161352" phraseText="Atropine" preferredWord="Atropinum, atropine" semType="phsu"/><RxNorm RxCui="1223"/></Normalization></entity><drugInteraction id="Dailymed.ad8916e7-206e-409e-2582-30d072845dd4.s.7.ddi.1"><interaction trigger="Dailymed.ad8916e7-206e-409e-2582-30d072845dd4.s.7.e.1"><relations><relation type="hasPrecipitant"><entity id="Dailymed.ad8916e7-206e-409e-2582-30d072845dd4.s.7.e.3"/></relation><relation type="hasObject"><entity id="Dailymed.ad8916e7-206e-409e-2582-30d072845dd4.s.7.e.2"/></relation></relations></interaction></drugInteraction><pair ddi="true" e1="Dailymed.ad8916e7-206e-409e-2582-30d072845dd4.s.7.e.3" e2="Dailymed.ad8916e7-206e-409e-2582-30d072845dd4.s.7.e.2" trigger="Dailymed.ad8916e7-206e-409e-2582-30d072845dd4.s.7.e.1" type="Decrease_Interaction"/></sentence><positiveExamples number="1"/><negativeExamples number="2"/></document>